himpunan_team2/__init__.py
himpunan_team2/himpunan.py
himpunan_team2-0.1.0.dist-info/METADATA
himpunan_team2-0.1.0.dist-info/WHEEL
himpunan_team2-0.1.0.dist-info/top_level.txt
himpunan_team2-0.1.0.dist-info/RECORD
