Metadata-Version: 2.1
Name: himpunan-team2
Version: 0.1.0
Summary: Package Python untuk operasi himpunan dengan fitur tambahan.
Author: Alvin Yuga Pramana, Jason Bintang Setiawan, Javin Erasmus Clementino
